binance/__init__.py
binance/__version__.py
binance/api.py
binance/error.py
binance/delivery/__init__.py
binance/delivery/account.py
binance/delivery/data_stream.py
binance/delivery/market.py
binance/futures/__init__.py
binance/futures/account.py
binance/futures/data_stream.py
binance/futures/market.py
binance/lib/__init__.py
binance/lib/enums.py
binance/lib/utils.py
binance/websocket/__init__.py
binance/websocket/binance_client_factory.py
binance/websocket/binance_client_protocol.py
binance/websocket/binance_socket_manager.py
binance/websocket/websocket_client.py
binance/websocket/delivery/__init__.py
binance/websocket/delivery/websocket_client.py
binance/websocket/futures/__init__.py
binance/websocket/futures/websocket_client.py
binance_futures_python_sdk-1.7.dist-info/LICENSE.md
binance_futures_python_sdk-1.7.dist-info/METADATA
binance_futures_python_sdk-1.7.dist-info/WHEEL
binance_futures_python_sdk-1.7.dist-info/top_level.txt
binance_futures_python_sdk-1.7.dist-info/RECORD
